hallyd/__init__.py
hallyd/bindle.py
hallyd/cleanup.py
hallyd/coding.py
hallyd/disk.py
hallyd/fs.py
hallyd/fs_monitor.py
hallyd/ipc.py
hallyd/ipc_hub.py
hallyd/lang.py
hallyd/net.py
hallyd/py_module.py
hallyd/services.py
hallyd/subprocess.py
hallyd/terminal.py
hallyd/typing.py
hallyd/asset/__init__.py
hallyd/asset/data.py
hallyd/asset/-static/helpers/call_action.py
hallyd/asset/-static/helpers/call_function.py
hallyd-0.9009.36.dist-info/METADATA
hallyd-0.9009.36.dist-info/WHEEL
hallyd-0.9009.36.dist-info/top_level.txt
hallyd-0.9009.36.dist-info/RECORD
