Metadata-Version: 2.4
Name: hallyd
Version: 0.9009.36
Summary: Various tools for filesystem, io, processes, other stuff.
Home-page: https://pseudopolis.eu/pino/hallyd
Author: Josef Hahn
Author-email: hallyd@pseudopolis.eu
License: AGPL 3
Keywords: python software development file filesystem path process text
Dynamic: author
Dynamic: author-email
Dynamic: description
Dynamic: description-content-type
Dynamic: home-page
Dynamic: keywords
Dynamic: license
Dynamic: summary
